README.txt
setup.py
MDTools.egg-info/PKG-INFO
MDTools.egg-info/SOURCES.txt
MDTools.egg-info/dependency_links.txt
MDTools.egg-info/requires.txt
MDTools.egg-info/top_level.txt
mdtools/__init__.py
mdtools/metadata.py