Metadata-Version: 1.1
Name: MDTools
Version: 0.0.2
Summary: A module to create XML metadata
Home-page: http://github.com/neondps/MDTools
Author: Edmund Hart
Author-email: emh@emhart.info
License: BSD
Keywords: XML metadata
Platform: UNKNOWN
Classifier: Development Status :: 3 - Alpha
Classifier: Intended Audience :: Science/Research
Classifier: Topic :: Utilities
Classifier: License :: OSI Approved :: BSD License
